tiffler/__init__.py
tiffler/tiffler.py
tiffler-0.1.11.dist-info/METADATA
tiffler-0.1.11.dist-info/WHEEL
tiffler-0.1.11.dist-info/top_level.txt
tiffler-0.1.11.dist-info/RECORD
