Metadata-Version: 2.1
Name: tiffler
Version: 0.1.11
Summary: This Niffler finds shiny variables in text
Home-page: UNKNOWN
Author: nghoangdat
Author-email: dat.nh.216@gmail.com
License: UNKNOWN
Platform: UNKNOWN
Classifier: Programming Language :: Python :: 3
Classifier: License :: OSI Approved :: MIT License
Classifier: Operating System :: OS Independent
Requires-Python: >=3.6
